novals/__init__.py
NoVals-1.0.1.dist-info/LICENSE
NoVals-1.0.1.dist-info/METADATA
NoVals-1.0.1.dist-info/WHEEL
NoVals-1.0.1.dist-info/top_level.txt
NoVals-1.0.1.dist-info/RECORD
