Metadata-Version: 2.1
Name: NoVals
Version: 1.0.1
Summary: Throws an error if any literals are in the source code, to help with verifying NoVals Code Golf solutions
Home-page: https://github.com/ThePythonist/NoVals
Author: Morgan Saville
Author-email: gbt505@hotmail.com
License: UNKNOWN
Platform: UNKNOWN
Classifier: Programming Language :: Python :: 3
Classifier: License :: OSI Approved :: MIT License
Classifier: Operating System :: OS Independent
